cell_runner/__init__.py
cell_runner/runner.py
tests/__init__.py
tests/test_runner.py
cell_runner-0.2.dist-info/LICENSE
cell_runner-0.2.dist-info/METADATA
cell_runner-0.2.dist-info/WHEEL
cell_runner-0.2.dist-info/entry_points.txt
cell_runner-0.2.dist-info/top_level.txt
cell_runner-0.2.dist-info/RECORD
