Metadata-Version: 2.1
Name: cell_runner
Version: 0.2
Summary: A package to run Jupyter notebook cells from the command line.
Home-page: https://github.com/chinthasaicharan/jupyter-cell-runner
Author: Chintha Sai Charan
Author-email: saicharanchintha8888@gmail.com
Classifier: Programming Language :: Python :: 3
Classifier: License :: OSI Approved :: MIT License
Classifier: Operating System :: OS Independent
Requires-Python: >=3.6
License-File: LICENSE
